Whit3_H4t_Sc4nn3r_Fir5t/__init__.py
Whit3_H4t_Sc4nn3r_Fir5t-0.0.1.dist-info/METADATA
Whit3_H4t_Sc4nn3r_Fir5t-0.0.1.dist-info/WHEEL
Whit3_H4t_Sc4nn3r_Fir5t-0.0.1.dist-info/top_level.txt
Whit3_H4t_Sc4nn3r_Fir5t-0.0.1.dist-info/RECORD
